CONTRIBUTING.rst
LICENSE.txt
MANIFEST.in
README.rst
setup.cfg
setup.py
pswingw2/__init__.py
pswingw2/client.py
pswingw2/config_defaults.py
pswingw2/serialization.py
pswingw2/shell.py
pswingw2/validation.py
pswingw2.egg-info/PKG-INFO
pswingw2.egg-info/SOURCES.txt
pswingw2.egg-info/dependency_links.txt
pswingw2.egg-info/entry_points.txt
pswingw2.egg-info/requires.txt
pswingw2.egg-info/top_level.txt