Metadata-Version: 1.1
Name: pswingw2
Version: 0.2
Summary: A package for sending SMS messages using the PSWinCom LINK SMS Gateway.
Home-page: https://github.com/ZettaIO/pswingw2py
Author: Einar Forselv
Author-email: eforselv@gmail.com
License: MIT
Download-URL: https://github.com/ZettaIO/pswingw2py/archive/0.1.tar.gz
Keywords: sms,pswin,linkmobility
Platform: UNKNOWN
Classifier: Development Status :: 4 - Beta
Classifier: Programming Language :: Python
Classifier: Programming Language :: Python :: 3
Classifier: Intended Audience :: Developers
Classifier: Topic :: Communications :: Telephony
Classifier: Topic :: Software Development :: Libraries :: Python Modules
Classifier: License :: OSI Approved :: MIT License
Classifier: Operating System :: OS Independent
